LICENSE
MANIFEST.in
README.rst
setup.py
mailchimpworker/__init__.py
mailchimpworker/admin.py
mailchimpworker/apps.py
mailchimpworker/models.py
mailchimpworker/tasks.py
mailchimpworker/tests.py
mailchimpworker.egg-info/PKG-INFO
mailchimpworker.egg-info/SOURCES.txt
mailchimpworker.egg-info/dependency_links.txt
mailchimpworker.egg-info/requires.txt
mailchimpworker.egg-info/top_level.txt