Metadata-Version: 1.0
Name: mailchimpworker
Version: 0.17
Summary: UNKNOWN
Home-page: UNKNOWN
Author: a_igin
Author-email: a_igin@mail.ru
License: MIT License
Platform: UNKNOWN
